greeting/__init__.py
greeting/admin.py
greeting/apps.py
greeting/models.py
greeting/tests.py
greeting/urls.py
greeting/views.py
greeting/static/greeting/style.css
greeting/templates/greeting/index.html
greeting_green-0.0.5.dist-info/METADATA
greeting_green-0.0.5.dist-info/WHEEL
greeting_green-0.0.5.dist-info/licenses/LICENSE.txt
greeting_green-0.0.5.dist-info/RECORD
